mozilla_django_oidc_db/__init__.py
mozilla_django_oidc_db/admin.py
mozilla_django_oidc_db/apps.py
mozilla_django_oidc_db/backends.py
mozilla_django_oidc_db/checks.py
mozilla_django_oidc_db/config.py
mozilla_django_oidc_db/constants.py
mozilla_django_oidc_db/exceptions.py
mozilla_django_oidc_db/fields.py
mozilla_django_oidc_db/forms.py
mozilla_django_oidc_db/jwt.py
mozilla_django_oidc_db/middleware.py
mozilla_django_oidc_db/models.py
mozilla_django_oidc_db/plugins.py
mozilla_django_oidc_db/py.typed
mozilla_django_oidc_db/registry.py
mozilla_django_oidc_db/schemas.py
mozilla_django_oidc_db/signals.py
mozilla_django_oidc_db/typing.py
mozilla_django_oidc_db/utils.py
mozilla_django_oidc_db/views.py
mozilla_django_oidc_db/locale/nl/LC_MESSAGES/django.po
mozilla_django_oidc_db/migrations/0001_initial_to_v015.py
mozilla_django_oidc_db/migrations/0001_initial_to_v023.py
mozilla_django_oidc_db/migrations/0002_migrate_to_claim_field.py
mozilla_django_oidc_db/migrations/0003_openidconnectconfig_oidc_keycloak_idp_hint_and_more.py
mozilla_django_oidc_db/migrations/0004_remove_openidconnectconfig_oidc_exempt_urls.py
mozilla_django_oidc_db/migrations/0005_alter_openidconnectconfig_claim_mapping.py
mozilla_django_oidc_db/migrations/0006_oidcprovider_oidcclient.py
mozilla_django_oidc_db/migrations/0007_migrate_oidc_data.py
mozilla_django_oidc_db/migrations/0008_delete_openidconnectconfig.py
mozilla_django_oidc_db/migrations/__init__.py
mozilla_django_oidc_db/setup_configuration/__init__.py
mozilla_django_oidc_db/setup_configuration/models.py
mozilla_django_oidc_db/setup_configuration/steps.py
mozilla_django_oidc_db/templates/admin/oidc_failure.html
mozilla_django_oidc_db/templatetags/__init__.py
mozilla_django_oidc_db/templatetags/mozilla_django_oidc_db.py
mozilla_django_oidc_db/tests/__init__.py
mozilla_django_oidc_db/tests/factories.py
mozilla_django_oidc_db/tests/mixins.py
mozilla_django_oidc_db/tests/utils.py
mozilla_django_oidc_db-1.1.1.dist-info/licenses/LICENSE
mozilla_django_oidc_db-1.1.1.dist-info/METADATA
mozilla_django_oidc_db-1.1.1.dist-info/WHEEL
mozilla_django_oidc_db-1.1.1.dist-info/top_level.txt
mozilla_django_oidc_db-1.1.1.dist-info/RECORD
