Metadata-Version: 2.4
Name: mozilla-django-oidc-db
Version: 1.1.1
Summary: A database-backed configuration for mozilla-django-oidc
Author-email: Maykin Media <support@maykinmedia.nl>
License-Expression: MIT
Project-URL: Homepage, https://github.com/maykinmedia/mozilla-django-oidc-db
Project-URL: Documentation, https://mozilla-django-oidc-db.readthedocs.io/en/latest/
Project-URL: Bug Tracker, https://github.com/maykinmedia/mozilla-django-oidc-db/issues
Project-URL: Source Code, https://github.com/maykinmedia/mozilla-django-oidc-db
Project-URL: Changelog, https://github.com/maykinmedia/mozilla-django-oidc-db/blob/master/CHANGELOG.rst
Keywords: OIDC,django,database,authentication
Classifier: Development Status :: 5 - Production/Stable
Classifier: Framework :: Django
Classifier: Framework :: Django :: 4.2
Classifier: Framework :: Django :: 5.2
Classifier: Intended Audience :: Developers
Classifier: Operating System :: Unix
Classifier: Operating System :: MacOS
Classifier: Operating System :: Microsoft :: Windows
Classifier: Programming Language :: Python :: 3.12
Classifier: Programming Language :: Python :: 3.13
Classifier: Topic :: Software Development :: Libraries :: Python Modules
Requires-Python: >=3.12
License-File: LICENSE
Requires-Dist: django>=4.2
Requires-Dist: django-jsonform>=2.12
Requires-Dist: glom
Requires-Dist: mozilla-django-oidc>=3.0.0
Requires-Dist: typing-extensions>=4.0.0
Provides-Extra: setup-configuration
Requires-Dist: django-setup-configuration>=0.11.0; extra == "setup-configuration"
Provides-Extra: tests
Requires-Dist: psycopg; extra == "tests"
Requires-Dist: pytest; extra == "tests"
Requires-Dist: pytest-cov; extra == "tests"
Requires-Dist: pytest-django; extra == "tests"
Requires-Dist: pytest-mock; extra == "tests"
Requires-Dist: pytest-recording; extra == "tests"
Requires-Dist: requests-mock; extra == "tests"
Requires-Dist: factory-boy; extra == "tests"
Requires-Dist: pyquery; extra == "tests"
Requires-Dist: tox; extra == "tests"
Requires-Dist: ruff; extra == "tests"
Requires-Dist: pyright; extra == "tests"
Requires-Dist: django-stubs; extra == "tests"
Provides-Extra: docs
Requires-Dist: sphinx; extra == "docs"
Requires-Dist: sphinx-rtd-theme; extra == "docs"
Provides-Extra: release
Requires-Dist: bump-my-version; extra == "release"
Dynamic: license-file
